llm_orc/__init__.py
llm_orc/cli.py
llm_orc/cli_commands.py
llm_orc/cli_completion.py
llm_orc/menu_system.py
llm_orc/py.typed
llm_orc/agents/__init__.py
llm_orc/agents/enhanced_script_agent.py
llm_orc/agents/script_agent.py
llm_orc/cli_library/__init__.py
llm_orc/cli_library/library.py
llm_orc/cli_modules/commands/__init__.py
llm_orc/cli_modules/commands/auth_commands.py
llm_orc/cli_modules/commands/config_commands.py
llm_orc/cli_modules/commands/script_commands.py
llm_orc/cli_modules/utils/__init__.py
llm_orc/cli_modules/utils/auth_utils.py
llm_orc/cli_modules/utils/cli_utils.py
llm_orc/cli_modules/utils/config_utils.py
llm_orc/cli_modules/utils/json_renderer.py
llm_orc/cli_modules/utils/performance_data.py
llm_orc/cli_modules/utils/provider_utils.py
llm_orc/cli_modules/utils/rich_progress_controller.py
llm_orc/cli_modules/utils/visualization.py
llm_orc/cli_modules/utils/visualization.py.backup
llm_orc/cli_modules/utils/visualization/__init__.py
llm_orc/cli_modules/utils/visualization/dependency.py
llm_orc/cli_modules/utils/visualization/performance_metrics.py
llm_orc/cli_modules/utils/visualization/results_display.py
llm_orc/cli_modules/utils/visualization/streaming.py
llm_orc/contracts/__init__.py
llm_orc/contracts/contract_validator.py
llm_orc/contracts/script_contract.py
llm_orc/core/__init__.py
llm_orc/core/artifacts/__init__.py
llm_orc/core/auth/__init__.py
llm_orc/core/auth/authentication.py
llm_orc/core/auth/oauth_client.py
llm_orc/core/auth/oauth_flows.py
llm_orc/core/communication/__init__.py
llm_orc/core/communication/protocol.py
llm_orc/core/config/__init__.py
llm_orc/core/config/config_manager.py
llm_orc/core/config/ensemble_config.py
llm_orc/core/config/roles.py
llm_orc/core/events/__init__.py
llm_orc/core/events/base.py
llm_orc/core/events/script_interaction.py
llm_orc/core/events/script_schemas.py
llm_orc/core/execution/__init__.py
llm_orc/core/execution/adaptive_resource_manager.py
llm_orc/core/execution/agent_execution_coordinator.py
llm_orchestra-0.13.0.dist-info/METADATA
llm_orchestra-0.13.0.dist-info/WHEEL
llm_orchestra-0.13.0.dist-info/entry_points.txt
llm_orchestra-0.13.0.dist-info/licenses/LICENSE
llm_orchestra-0.13.0.dist-info/RECORD
