Metadata-Version: 2.4
Name: llm-orchestra
Version: 0.13.0
Summary: Multi-agent LLM communication system with ensemble orchestration
Project-URL: Homepage, https://github.com/mrilikecoding/llm-orc
Project-URL: Repository, https://github.com/mrilikecoding/llm-orc
Project-URL: Bug Tracker, https://github.com/mrilikecoding/llm-orc/issues
Project-URL: Documentation, https://github.com/mrilikecoding/llm-orc#readme
Author-email: Nathan Green <contact@nate.green>
License: MIT License
License-File: LICENSE
Keywords: agents,ai,ensemble,llm,multi-agent,orchestration
Classifier: Development Status :: 4 - Beta
Classifier: Intended Audience :: Developers
Classifier: Intended Audience :: Science/Research
Classifier: License :: OSI Approved :: MIT License
Classifier: Programming Language :: Python :: 3
Classifier: Programming Language :: Python :: 3.11
Classifier: Programming Language :: Python :: 3.12
Classifier: Topic :: Scientific/Engineering :: Artificial Intelligence
Classifier: Topic :: Software Development :: Libraries :: Python Modules
Requires-Python: >=3.11
Requires-Dist: aiohttp>=3.12.14
Requires-Dist: anthropic
Requires-Dist: click
Requires-Dist: cryptography
Requires-Dist: fastapi>=0.115.0
Requires-Dist: google-genai
Requires-Dist: mcp>=1.0.0
Requires-Dist: ollama
Requires-Dist: psutil>=5.9.0
Requires-Dist: pydantic
Requires-Dist: python-dotenv>=1.1.1
Requires-Dist: pyyaml
Requires-Dist: requests>=2.32.4
Requires-Dist: rich>=13.0.0
Requires-Dist: uvicorn>=0.32.0
Requires-Dist: websockets
Provides-Extra: dev
Requires-Dist: build; extra == 'dev'
Requires-Dist: mypy>=1.5.0; extra == 'dev'
Requires-Dist: pip-audit>=2.6.0; extra == 'dev'
Requires-Dist: pytest-asyncio>=0.21.0; extra == 'dev'
Requires-Dist: pytest-bdd>=7.0.0; extra == 'dev'
Requires-Dist: pytest-cov>=4.1.0; extra == 'dev'
Requires-Dist: pytest>=7.4.0; extra == 'dev'
Requires-Dist: ruff>=0.0.287; extra == 'dev'
Requires-Dist: twine; extra == 'dev'
